m365_mcp/__init__.py
m365_mcp/account_type.py
m365_mcp/auth.py
m365_mcp/background_worker.py
m365_mcp/cache.py
m365_mcp/cache_config.py
m365_mcp/cache_migration.py
m365_mcp/cache_warming.py
m365_mcp/encryption.py
m365_mcp/graph.py
m365_mcp/health_check.py
m365_mcp/logging_config.py
m365_mcp/mcp_instance.py
m365_mcp/search_router.py
m365_mcp/server.py
m365_mcp/tools.py
m365_mcp/validators.py
m365_mcp/migrations/001_init_cache.sql
m365_mcp/tools/__init__.py
m365_mcp/tools/account.py
m365_mcp/tools/cache_tools.py
m365_mcp/tools/calendar.py
m365_mcp/tools/contact.py
m365_mcp/tools/email.py
m365_mcp/tools/email_folders.py
m365_mcp/tools/email_rules.py
m365_mcp/tools/file.py
m365_mcp/tools/folder.py
m365_mcp/tools/search.py
m365_mcp/tools/server.py
m365_mcp-0.2.1.dist-info/METADATA
m365_mcp-0.2.1.dist-info/WHEEL
m365_mcp-0.2.1.dist-info/entry_points.txt
m365_mcp-0.2.1.dist-info/RECORD
