Metadata-Version: 2.4
Name: m365-mcp
Version: 0.2.1
Summary: Microsoft 365 MCP server for Outlook, Calendar, and OneDrive with multi-account support
Project-URL: Homepage, https://github.com/robin-collins/m365-mcp
Project-URL: Repository, https://github.com/robin-collins/m365-mcp
Project-URL: Issues, https://github.com/robin-collins/m365-mcp/issues
Project-URL: Documentation, https://github.com/robin-collins/m365-mcp#readme
Author-email: robin-collins <robin.f.collins@outlook.com>, elyx <elio@pascarelli.com>
License: MIT
Keywords: ai,calendar,mcp,microsoft-365,microsoft-graph,onedrive,outlook
Classifier: Development Status :: 3 - Alpha
Classifier: Intended Audience :: Developers
Classifier: License :: OSI Approved :: MIT License
Classifier: Programming Language :: Python :: 3
Classifier: Programming Language :: Python :: 3.12
Classifier: Topic :: Software Development :: Libraries :: Python Modules
Requires-Python: >=3.12
Requires-Dist: coverage>=7.10.7
Requires-Dist: fastapi>=0.115.0
Requires-Dist: fastmcp>=2.8.0
Requires-Dist: httpx>=0.28.1
Requires-Dist: keyring>=25.6.0
Requires-Dist: msal>=1.32.3
Requires-Dist: pyjwt>=2.10.1
Requires-Dist: pysqlcipher3>=1.2.0
Requires-Dist: python-dotenv>=1.1.0
Requires-Dist: sqlcipher3>=0.5.4
Requires-Dist: uvicorn>=0.32.0
